COPYRIGHTS.txt
LICENSE
MANIFEST.in
NEWS.md
README.rst
requirements.txt
setup.cfg
setup.py
.eggs/README.txt
.eggs/pytest_runner-3.0-py2.7.egg/ptr.py
.eggs/pytest_runner-3.0-py2.7.egg/EGG-INFO/entry_points.txt
.eggs/pytest_runner-3.0-py2.7.egg/EGG-INFO/namespace_packages.txt
.eggs/pytest_runner-3.0-py2.7.egg/EGG-INFO/requires.txt
.eggs/pytest_runner-3.0-py2.7.egg/EGG-INFO/top_level.txt
documentation/docs/conf.py
documentation/docs/_build/html/_sources/index.rst.txt
documentation/docs/_build/html/_sources/modules.rst.txt
documentation/docs/_build/html/_sources/page.rst.txt
documentation/docs/_build/html/_sources/_autosummary/big_text_files.rst.txt
documentation/docs/_build/html/_sources/_autosummary/docs_matrix.rst.txt
documentation/docs/_build/html/_sources/_autosummary/token_stats.rst.txt
documentation/docs/_build/html/_sources/_autosummary/tokenizer.rst.txt
documentation/docs/_build/html/_sources/_autosummary/utils.rst.txt
documentation/documentation_classes/big_text_files.py
documentation/documentation_classes/docs_matrix.py
documentation/documentation_classes/token_stats.py
documentation/documentation_classes/tokenizer.py
documentation/documentation_classes/utils.py
test/__init__.py
test/conftest.py
test/params_big_files.py
test/params_term_matrix.py
test/params_textTiny.py
test/params_token_stats.py
test/params_tokenizer.py
test/params_utils.py
test/test_big_files.py
test/test_term_matrix.py
test/test_token_stats.py
test/test_tokenizer.py
test/test_utils.py
test/VOCAB/batch1.txt
test/VOCAB/batch2.txt
test/VOCAB_token_stats/VOCAB_token_stats0.txt
test/VOCAB_token_stats/VOCAB_token_stats1.txt
test/parse_loader/batch1.txt
test/parse_loader/batch2.txt
test/tests_load_folder/TOKEN_ngram_PARSER.txt
test/tests_load_folder/VOCAB_token_stats.txt
test/tests_load_folder/term_matrix_file.csv
test/tests_load_folder/term_matrix_file.txt
test/tests_load_folder/tok_file.txt
test/tests_save_folder/empty_f.txt
textTinyPy/__init__.py
textTinyPy/textTinyPy.cpp
textTinyPy/textTinyPy.pxd
textTinyPy/textTinyPy.pyx
textTinyPy/textTinyPy.so
textTinyPy.egg-info/PKG-INFO
textTinyPy.egg-info/SOURCES.txt
textTinyPy.egg-info/dependency_links.txt
textTinyPy.egg-info/requires.txt
textTinyPy.egg-info/top_level.txt
textTinyPy/cpp_src/UTILS.h
textTinyPy/cpp_src/batch_tokenization.cpp
textTinyPy/cpp_src/batch_tokenization.h
textTinyPy/cpp_src/hash.h
textTinyPy/cpp_src/ngram_stemmer.cpp
