Metadata-Version: 1.1
Name: textTinyPy
Version: 0.0.4
Summary: text processing functions for small or big data files
Home-page: https://github.com/mlampros/textTinyPy
Author: Lampros Mouselimis
Author-email: mouselimislampros@gmail.com
License: GNU General Public License (GPL) + COPYRIGHTS.txt
Platform: UNKNOWN
Classifier: Development Status :: 3 - Alpha
Classifier: Intended Audience :: End Users/Desktop
Classifier: Natural Language :: English
Classifier: Operating System :: POSIX :: Linux
Classifier: Programming Language :: Python :: 2.7
Classifier: Topic :: Software Development :: Libraries :: Python Modules
